setup.py
messenger_server_may.egg-info/PKG-INFO
messenger_server_may.egg-info/SOURCES.txt
messenger_server_may.egg-info/dependency_links.txt
messenger_server_may.egg-info/requires.txt
messenger_server_may.egg-info/top_level.txt
server/__init__.py
server/server.py
server/server_gui.py
server/common/__init__.py
server/common/decorators.py
server/common/descriptors.py
server/common/errors.py
server/common/metaclasses.py
server/common/utils.py
server/common/variables.py
server/doc/__init__.py
server/doc/source/__init__.py
server/doc/source/conf.py
server/log/__init__.py
server/log/config/__init__.py
server/log/config/client_log_config.py
server/log/config/server_log_config.py
server/server_dir/__init__.py
server/server_dir/add_user.py
server/server_dir/config_window.py
server/server_dir/core.py
server/server_dir/main_window.py
server/server_dir/remove_user.py
server/server_dir/server_database.py
server/server_dir/stat_window.py
server/unit_tests/__init__.py
server/unit_tests/test_client.py
server/unit_tests/test_server.py
server/unit_tests/test_utils.py