Metadata-Version: 2.1
Name: messenger-server-may
Version: 0.9.1
Summary: server packet
Home-page: UNKNOWN
Author: Egor Varlamov
License: UNKNOWN
Platform: UNKNOWN
